LICENSE
greenmountainpower/__init__.py
greenmountainpower/api.py
greenmountainpower/exceptions.py
greenmountainpower-0.0.5.dist-info/LICENSE
greenmountainpower-0.0.5.dist-info/WHEEL
greenmountainpower-0.0.5.dist-info/METADATA
greenmountainpower-0.0.5.dist-info/RECORD
