Metadata-Version: 2.1
Name: greenmountainpower
Version: 0.0.5
Summary: This is an unofficial Python client that uses the undocumented API for Green Mountain Power accounts.
Home-page: https://github.com/sbrinkerhoff/greenmountainpower/
License: MIT
Author: Kodey Converse
Author-email: kodey@conve.rs
Requires-Python: >=3.7,<4.0
Classifier: License :: OSI Approved :: MIT License
Classifier: Programming Language :: Python :: 3
Classifier: Programming Language :: Python :: 3.7
Classifier: Programming Language :: Python :: 3.8
Classifier: Programming Language :: Python :: 3.9
Classifier: Programming Language :: Python :: 3.10
Classifier: Programming Language :: Python :: 3.11
Requires-Dist: oauthlib (>=3,<4)
Requires-Dist: requests (>=2,<3)
Requires-Dist: requests-oauthlib (>=1,<2)
